notmath/__init__.py
notmath/main.py
notmath-0.1.0.dist-info/METADATA
notmath-0.1.0.dist-info/WHEEL
notmath-0.1.0.dist-info/top_level.txt
notmath-0.1.0.dist-info/RECORD
