Metadata-Version: 2.4
Name: notmath
Version: 0.1.0
Summary: it is not for math
Home-page: https://github.com/yourusername/my_library
Author: Beka Kopadze
Author-email: beka.kopadze@iliauni.edu.ge
Classifier: Programming Language :: Python :: 3
Classifier: License :: OSI Approved :: MIT License
Classifier: Operating System :: OS Independent
Requires-Python: >=3.6
Dynamic: author
Dynamic: author-email
Dynamic: classifier
Dynamic: description-content-type
Dynamic: home-page
Dynamic: requires-python
Dynamic: summary
